hearthsim/identity/__init__.py
hearthsim/identity/accounts/__init__.py
hearthsim/identity/accounts/models.py
hearthsim/identity/accounts/migrations/0001_initial.py
hearthsim/identity/accounts/migrations/0002_auto_20171226_1303.py
hearthsim/identity/accounts/migrations/0003_auto_20181005_2138.py
hearthsim/identity/accounts/migrations/__init__.py
hearthsim/identity/api/__init__.py
hearthsim/identity/api/models.py
hearthsim/identity/api/migrations/0001_initial.py
hearthsim/identity/api/migrations/__init__.py
hearthsim/identity/oauth2/__init__.py
hearthsim/identity/oauth2/models.py
hearthsim/identity/oauth2/permissions.py
hearthsim/identity/oauth2/migrations/0001_initial.py
hearthsim/identity/oauth2/migrations/__init__.py
hearthsim_identity-3.2.1.dist-info/LICENSE
hearthsim_identity-3.2.1.dist-info/METADATA
hearthsim_identity-3.2.1.dist-info/WHEEL
hearthsim_identity-3.2.1.dist-info/top_level.txt
hearthsim_identity-3.2.1.dist-info/RECORD
