Metadata-Version: 2.1
Name: hearthsim-identity
Version: 3.2.1
Summary: HearthSim Identity ORM models
Home-page: https://github.com/HearthSim/hearthsim-identity
Author: Jerome Leclanche
Author-email: jerome@leclan.ch
License: UNKNOWN
Download-URL: https://github.com/HearthSim/hearthsim-identity/tarball/master
Keywords: hearthsim,django
Platform: UNKNOWN
Classifier: Development Status :: 4 - Beta
Classifier: Environment :: Web Environment
Classifier: Framework :: Django
Classifier: Framework :: Django :: 2.0
Classifier: Intended Audience :: Developers
Classifier: License :: OSI Approved :: MIT License
Classifier: Programming Language :: Python :: 3
Classifier: Programming Language :: Python :: 3.6
Classifier: Topic :: Internet :: WWW/HTTP
Requires-Dist: Django (>=2.0)
Requires-Dist: django-intenumfield (>=1.4.0)
Requires-Dist: hearthstone
